light-sensor/__init__.py
light-sensor/tinycircuits_tsl2572.py
tinycircuits_tsl2572/__init__.py
tinycircuits_tsl2572/tinycircuits_tsl2572.py
tinycircuits_tsl2572-0.0.7.dist-info/LICENSE
tinycircuits_tsl2572-0.0.7.dist-info/METADATA
tinycircuits_tsl2572-0.0.7.dist-info/WHEEL
tinycircuits_tsl2572-0.0.7.dist-info/top_level.txt
tinycircuits_tsl2572-0.0.7.dist-info/RECORD
