Metadata-Version: 2.1
Name: tinycircuits-tsl2572
Version: 0.0.7
Summary: Wireling Ambient Light Sensor Python library
Home-page: https://github.com/TinyCircuits/TinyCircuits-Wireling-Light-Sensor-Python-AST1012
Author: TinyCircuits
Author-email: info@tinycircuits.com
License: UNKNOWN
Platform: UNKNOWN
Classifier: Programming Language :: Python :: 3
Classifier: License :: OSI Approved :: GNU General Public License v3 (GPLv3)
Classifier: Operating System :: OS Independent
Requires-Python: >=3.6
